{"cameraMode":{"drawMode":0,"name":"Shaded","section":"Shading Mode"},"sceneLighting":false,"audioPlay":false,"sceneViewState":{"showFog":true,"showMaterialUpdate":false,"showSkybox":false,"showFlares":true,"showImageEffects":true,"showParticleSystems":true},"in2DMode":false,"pivot":{"x":-12.744824409484864,"y":0.895936906337738,"z":-39.56182098388672},"rotation":{"x":-0.00132361997384578,"y":-0.9657343029975891,"z":0.25949305295944216,"w":-0.00492734694853425},"size":2.6608707904815676,"orthographic":false}